LICENSE
README.md
pyproject.toml
setup.py
dailycheckin/__init__.py
dailycheckin/__version__.py
dailycheckin/configs.py
dailycheckin/main.py
dailycheckin/acfun/__init__.py
dailycheckin/acfun/main.py
dailycheckin/aliyun/__init__.py
dailycheckin/aliyun/main.py
dailycheckin/aolaxing/__init__.py
dailycheckin/aolaxing/main.py
dailycheckin/baidu/__init__.py
dailycheckin/baidu/main.py
dailycheckin/baiduwp/__init__.py
dailycheckin/baiduwp/main.py
dailycheckin/bilibili/__init__.py
dailycheckin/bilibili/main.py
dailycheckin/enshan/__init__.py
dailycheckin/enshan/main.py
dailycheckin/ican/__init__.py
dailycheckin/ican/main.py
dailycheckin/imaotai/__init__.py
dailycheckin/imaotai/main.py
dailycheckin/iqiyi/__init__.py
dailycheckin/iqiyi/main.py
dailycheckin/kgqq/__init__.py
dailycheckin/kgqq/main.py
dailycheckin/mimotion/__init__.py
dailycheckin/mimotion/main.py
dailycheckin/smzdm/__init__.py
dailycheckin/smzdm/main.py
dailycheckin/tieba/__init__.py
dailycheckin/tieba/main.py
dailycheckin/utils/__init__.py
dailycheckin/utils/message.py
dailycheckin/v2ex/__init__.py
dailycheckin/v2ex/main.py
dailycheckin/youdao/__init__.py
dailycheckin/youdao/main.py
wood_dailycheckin.egg-info/PKG-INFO
wood_dailycheckin.egg-info/SOURCES.txt
wood_dailycheckin.egg-info/dependency_links.txt
wood_dailycheckin.egg-info/entry_points.txt
wood_dailycheckin.egg-info/not-zip-safe
wood_dailycheckin.egg-info/requires.txt
wood_dailycheckin.egg-info/top_level.txt