Metadata-Version: 2.4
Name: wood_dailycheckin
Version: 1.0.0
Home-page: https://sitoi.cn
Author: wood
Author-email: 445991004@qq.com
License: MIT
Project-URL: Documentation, https://sitoi.github.io/dailycheckin/
Classifier: License :: OSI Approved :: MIT License
Classifier: Programming Language :: Python :: 3.9
Classifier: Programming Language :: Python :: 3.12
Classifier: Programming Language :: Python :: Implementation :: CPython
Classifier: Programming Language :: Python :: Implementation :: PyPy
Requires-Python: >=3.9.0
License-File: LICENSE
Requires-Dist: pycryptodome~=3.17
Requires-Dist: requests~=2.25.1
Requires-Dist: rsa~=4.0
Requires-Dist: urllib3~=1.26.2
Dynamic: author
Dynamic: author-email
Dynamic: classifier
Dynamic: description
Dynamic: description-content-type
Dynamic: home-page
Dynamic: license
Dynamic: license-file
Dynamic: project-url
Dynamic: requires-python
